MANIFEST.in
README.md
setup.py
tokenleaderclient/__init__.py
tokenleaderclient/run_flask_app.py
tokenleaderclient.egg-info/PKG-INFO
tokenleaderclient.egg-info/SOURCES.txt
tokenleaderclient.egg-info/dependency_links.txt
tokenleaderclient.egg-info/entry_points.txt
tokenleaderclient.egg-info/not-zip-safe
tokenleaderclient.egg-info/requires.txt
tokenleaderclient.egg-info/top_level.txt
tokenleaderclient/acl/__init__.py
tokenleaderclient/acl/role_to_acl_map.yml
tokenleaderclient/acl/service_access_policy.yml
tokenleaderclient/client/__init__.py
tokenleaderclient/client/cli_parser.py
tokenleaderclient/client/client.py
tokenleaderclient/configs/__init__.py
tokenleaderclient/configs/cli_config.py
tokenleaderclient/configs/config_handler.py
tokenleaderclient/flaskapp/__init__.py
tokenleaderclient/flaskapp/APIroutes/__init__.py
tokenleaderclient/flaskapp/APIroutes/firstapi.py
tokenleaderclient/rbac/__init__.py
tokenleaderclient/rbac/enforcer.py
tokenleaderclient/rbac/policy.py
tokenleaderclient/rbac/wfc.py
tokenleaderclient/tests/__init__.py
tokenleaderclient/tests/base_tests.py
tokenleaderclient/tests/test_acl.py
tokenleaderclient/tests/test_acl_enforcer_decorator.py
tokenleaderclient/tests/testdata/__init__.py
tokenleaderclient/tests/testdata/role_to_acl_map.yml
tokenleaderclient/tests/testdata/service_access_policy.yml
tokenleaderclient/tests/testdata/test_general_configs.yml