Metadata-Version: 1.0
Name: tokenleaderclient
Version: 1.5.1
Summary: Client for token based authentication and role based access control
Home-page: https://github.com/prasenkr/tokenleaderclient
Author: Prasen Biswas
Author-email: prasenkrb@gmail.com
License: Apache Software License
Platform: UNKNOWN
